AutoGenerateMKD/__init__.py
AutoGenerateMKD/main.py
AutoGenerateMKD/mkdocs.yml
AutoGenerateMKD-0.0.11.data/data/mkdocs.yml
mkdocs_pagenav_generator/__init__.py
mkdocs_pagenav_generator/plugin.py
AutoGenerateMKD-0.0.11.dist-info/LICENSE
AutoGenerateMKD-0.0.11.dist-info/METADATA
AutoGenerateMKD-0.0.11.dist-info/WHEEL
AutoGenerateMKD-0.0.11.dist-info/entry_points.txt
AutoGenerateMKD-0.0.11.dist-info/top_level.txt
AutoGenerateMKD-0.0.11.dist-info/RECORD
